Metadata-Version: 2.1
Name: google-endpoints-api-management-tbafork
Version: 2.0.0.dev1
Summary: Google Endpoints API management
Home-page: https://github.com/cloudendpoints/endpoints-management-python
Author: Google Inc
Author-email: googleapis-packages@google.com
License: Apache License
Classifier: Development Status :: 4 - Beta
Classifier: Intended Audience :: Developers
Classifier: License :: OSI Approved :: Apache Software License
Classifier: Programming Language :: Python
Classifier: Programming Language :: Python :: 2
Classifier: Programming Language :: Python :: 2.7
Classifier: Programming Language :: Python :: Implementation :: CPython
License-File: LICENSE
Requires-Dist: backoff (>=2.00)
Requires-Dist: cachetools (>=5.0.0)
Requires-Dist: dogpile.cache (>=1.0.1)
Requires-Dist: google-cloud-monitoring (>=2.10.0)
Requires-Dist: google-cloud-service-control (>=1.5.0)
Requires-Dist: google-cloud-service-management (>=1.3.0)
Requires-Dist: pylru (>=1.0.9)
Requires-Dist: pyjwkest (>=1.0.0)
Requires-Dist: requests (>=2.10.0)
Requires-Dist: strict-rfc3339 (>=0.7)
Requires-Dist: webob (>=1.7.4)
